uvfile/__main__.py
uvfile-0.1.1.dist-info/METADATA
uvfile-0.1.1.dist-info/WHEEL
uvfile-0.1.1.dist-info/entry_points.txt
uvfile-0.1.1.dist-info/RECORD
