Metadata-Version: 2.4
Name: UVFile
Version: 0.1.1
Summary: Like Brewfile but for UV
Author-email: Bobronium <write@bobronium.me>
License: MIT
Keywords: brewfile,pipx,tools,uv,uvfile,uvx
Classifier: Development Status :: 3 - Alpha
Classifier: Framework :: Pytest
Classifier: Intended Audience :: Developers
Classifier: Operating System :: OS Independent
Classifier: Programming Language :: Python
Classifier: Programming Language :: Python :: 3 :: Only
Classifier: Programming Language :: Python :: 3.12
Classifier: Programming Language :: Python :: 3.13
Classifier: Programming Language :: Python :: Implementation :: CPython
Requires-Python: >=3.12
Requires-Dist: packaging
